alpaca_sqs_listener/__init__.py
alpaca_sqs_listener/sqs_listener.py
alpaca_sqs_listener-2022.1.1.dist-info/METADATA
alpaca_sqs_listener-2022.1.1.dist-info/WHEEL
alpaca_sqs_listener-2022.1.1.dist-info/entry_points.txt
alpaca_sqs_listener-2022.1.1.dist-info/top_level.txt
alpaca_sqs_listener-2022.1.1.dist-info/RECORD
